{
   "courses":[
      {
         "idCourse":"2",
         "idTypeCourse":"7",
         "idMatter":"125",
         "idTeacher":"25",
         "idClass":"4",
         "dateStart":"03-04-2020",
         "dateEnd":"03-04-2020",
         "presentTeacher":"Mireille l'Abeille",
         "comments":"HELLO"
      },
      {
         "idCourse":"2",
         "idTypeCourse":"7",
         "idMatter":"125",
         "idTeacher":"25",
         "idClass":"4",
         "dateStart":"03-04-2020",
         "dateEnd":"03-04-2020",
         "presentTeacher":"Marc Antoine",
         "comments":"HELLO"
      },
      {
         "idCourse":"2",
         "idTypeCourse":"7",
         "idMatter":"125",
         "idTeacher":"25",
         "idClass":"4",
         "dateStart":"04-04-2020",
         "dateEnd":"04-04-2020",
         "presentTeacher":"Arnold Schwarzenneger",
         "comments":"HELLO"
      },
      {
         "idCourse":"2",
         "idTypeCourse":"7",
         "idMatter":"125",
         "idTeacher":"25",
         "idClass":"4",
         "dateStart":"04-04-2020",
         "dateEnd":"03-04-2020",
         "presentTeacher":"Staline",
         "comments":"HELLO"
      },
      {
         "idCourse":"2",
         "idTypeCourse":"7",
         "idMatter":"125",
         "idTeacher":"25",
         "idClass":"4",
         "dateStart":"05-04-2020",
         "dateEnd":"03-04-2020",
         "presentTeacher":"Adolf Hitler",
         "comments":"HELLO"
      }
   ]
}
